README.md
setup.py
stereoscope.egg-info/PKG-INFO
stereoscope.egg-info/SOURCES.txt
stereoscope.egg-info/dependency_links.txt
stereoscope.egg-info/entry_points.txt
stereoscope.egg-info/not-zip-safe
stereoscope.egg-info/requires.txt
stereoscope.egg-info/top_level.txt
stsc/__init__.py
stsc/__main__.py
stsc/datasets.py
stsc/fit.py
stsc/look.py
stsc/models.py
stsc/parser.py
stsc/progress.py
stsc/run.py
stsc/test.py
stsc/utils.py